octis/__init__.py
octis/cli.py
octis/octis.py
octis/configuration/__init__.py
octis/configuration/citations.py
octis/configuration/defaults.py
octis/dashboard/__init__.py
octis/dashboard/experimentManager.py
octis/dashboard/frameworkScanner.py
octis/dashboard/queueManager.py
octis/dashboard/server.py
octis/dataset/__init__.py
octis/dataset/dataset.py
octis/dataset/downloader.py
octis/evaluation_metrics/__init__.py
octis/evaluation_metrics/classification_metrics.py
octis/evaluation_metrics/coherence_metrics.py
octis/evaluation_metrics/diversity_metrics.py
octis/evaluation_metrics/metrics.py
octis/evaluation_metrics/rbo.py
octis/evaluation_metrics/similarity_metrics.py
octis/evaluation_metrics/topic_significance_metrics.py
octis/evaluation_metrics/word_embeddings_rbo.py
octis/evaluation_metrics/word_embeddings_rbo_centroid.py
octis/models/CTM.py
octis/models/DETM.py
octis/models/ETM.py
octis/models/HDP.py
octis/models/LDA.py
octis/models/LDA_tomopy.py
octis/models/LSI.py
octis/models/NMF.py
octis/models/NMF_scikit.py
octis/models/NeuralLDA.py
octis/models/ProdLDA.py
octis/models/__init__.py
octis/models/base_etm.py
octis/models/model.py
octis/models/DETM_model/__init__.py
octis/models/DETM_model/data.py
octis/models/DETM_model/detm.py
octis/models/ETM_model/__init__.py
octis/models/ETM_model/data.py
octis/models/ETM_model/etm.py
octis/models/ETM_model/skipgram.py
octis/models/ETM_model/utils.py
octis/models/contextualized_topic_models/__init__.py
octis/models/contextualized_topic_models/contextualized_topic_models.py
octis/models/contextualized_topic_models/datasets/__init__.py
octis/models/contextualized_topic_models/datasets/dataset.py
octis/models/contextualized_topic_models/models/__init__.py
octis/models/contextualized_topic_models/models/ctm.py
octis/models/contextualized_topic_models/networks/__init__.py
octis/models/contextualized_topic_models/networks/decoding_network.py
octis/models/contextualized_topic_models/networks/inference_network.py
octis-1.14.0.dist-info/AUTHORS.rst
octis-1.14.0.dist-info/LICENSE
octis-1.14.0.dist-info/METADATA
octis-1.14.0.dist-info/WHEEL
octis-1.14.0.dist-info/entry_points.txt
octis-1.14.0.dist-info/top_level.txt
octis-1.14.0.dist-info/RECORD
