Metadata-Version: 2.1
Name: octis
Version: 1.14.0
Summary: OCTIS: a library for Optimizing and Comparing Topic Models.
Home-page: https://github.com/MIND-LAB/OCTIS
Author: Silvia Terragni
Author-email: s.terragni4@campus.unimib.it
License: MIT license
Keywords: octis
Platform: UNKNOWN
Classifier: Development Status :: 2 - Pre-Alpha
Classifier: Intended Audience :: Developers
Classifier: License :: OSI Approved :: MIT License
Classifier: Natural Language :: English
Classifier: Programming Language :: Python :: 3
Classifier: Programming Language :: Python :: 3.7
Classifier: Programming Language :: Python :: 3.8
Classifier: Programming Language :: Python :: 3.9
Requires-Python: >=3.7
License-File: LICENSE
License-File: AUTHORS.rst
Requires-Dist: gensim <5.0,>=4.2.0
Requires-Dist: nltk
Requires-Dist: pandas
Requires-Dist: spacy
Requires-Dist: scikit-learn ==1.1.0
Requires-Dist: scikit-optimize >=0.8.1
Requires-Dist: matplotlib
Requires-Dist: torch
Requires-Dist: numpy <2.0,>=1.23.0
Requires-Dist: libsvm
Requires-Dist: flask
Requires-Dist: sentence-transformers
Requires-Dist: requests
Requires-Dist: tomotopy
Requires-Dist: scipy <1.13
